floom/FloomClient.py
floom/FloomRequest.py
floom/FloomResponse.py
floom/__init__.py
floom/client.py
floom/models.py
floom/request.py
floom/utils.py
Floom-1.0.5.dist-info/METADATA
Floom-1.0.5.dist-info/WHEEL
Floom-1.0.5.dist-info/top_level.txt
Floom-1.0.5.dist-info/RECORD
